{
    "key": "group_64d6725ae8855",
    "title": "Block – Featured Work",
    "fields": [
        {
            "key": "field_64fb778e2725c",
            "label": "Featured Image Layout",
            "name": "featured_image_layout",
            "aria-label": "",
            "type": "true_false",
            "instructions": "",
            "required": 0,
            "conditional_logic": 0,
            "wrapper": {
                "width": "50",
                "class": "",
                "id": ""
            },
            "wpml_cf_preferences": 1,
            "message": "",
            "default_value": 0,
            "ui_on_text": "",
            "ui_off_text": "",
            "ui": 1
        },
        {
            "key": "field_64fb77ad2725d",
            "label": "Upload Image",
            "name": "image",
            "aria-label": "",
            "type": "image",
            "instructions": "Recommended image dimensions: 1284 x 530 pixels. If uploading an image with different dimensions, the image will be cropped in te center and stretched to fit.",
            "required": 1,
            "conditional_logic": [
                [
                    {
                        "field": "field_64fb778e2725c",
                        "operator": "==",
                        "value": "1"
                    }
                ]
            ],
            "wrapper": {
                "width": "50",
                "class": "",
                "id": ""
            },
            "wpml_cf_preferences": 1,
            "return_format": "id",
            "library": "all",
            "min_width": "",
            "min_height": "",
            "min_size": "",
            "max_width": "",
            "max_height": "",
            "max_size": "",
            "mime_types": "",
            "preview_size": "medium"
        },
        {
            "key": "field_64d6725b0b4fe",
            "label": "Select Resource",
            "name": "featured_resource",
            "aria-label": "",
            "type": "relationship",
            "instructions": "Select a featured resource from the left column. The resource in the right column will be displayed.",
            "required": 0,
            "conditional_logic": 0,
            "wrapper": {
                "width": "",
                "class": "",
                "id": ""
            },
            "wpml_cf_preferences": 1,
            "post_type": [
                "post"
            ],
            "post_status": [
                "publish"
            ],
            "taxonomy": [
                "resource_type:blog_news",
                "resource_type:case-studies",
                "resource_type:projects",
                "resource_type:reports-research",
                "resource_type:tools-guides"
            ],
            "filters": [
                "search",
                "taxonomy"
            ],
            "return_format": "id",
            "min": 1,
            "max": 1,
            "elements": "",
            "bidirectional": 0,
            "bidirectional_target": []
        }
    ],
    "location": [
        [
            {
                "param": "block",
                "operator": "==",
                "value": "acf\/featured-work"
            }
        ]
    ],
    "menu_order": 0,
    "position": "normal",
    "style": "default",
    "label_placement": "top",
    "instruction_placement": "label",
    "hide_on_screen": "",
    "active": true,
    "description": "",
    "show_in_rest": 0,
    "acfml_field_group_mode": "translation",
    "modified": 1694204943
}
